science/__init__.py
science-0.0.1.dist-info/METADATA
science-0.0.1.dist-info/WHEEL
science-0.0.1.dist-info/top_level.txt
science-0.0.1.dist-info/RECORD
