Metadata-Version: 2.4
Name: science
Version: 0.0.1
Summary: Science
Author-email: Andy Casey <andrew.casey@monash.edu>
Maintainer-email: Andy Casey <andrew.casey@monash.edu>
License: LICENSE.md
Keywords: science
Requires-Python: >=3.9
Requires-Dist: numpy
Provides-Extra: dev
Requires-Dist: pytest; extra == "dev"
Requires-Dist: pytest-cov; extra == "dev"
Requires-Dist: pytest-sugar; extra == "dev"
Requires-Dist: pre-commit; extra == "dev"
Requires-Dist: black; extra == "dev"
